mpipool/__init__.py
mpipool/_futures.py
mpipool/_multiprocessing.py
mpipool/exceptions.py
mpipool-2.2.1.dist-info/LICENSE
mpipool-2.2.1.dist-info/WHEEL
mpipool-2.2.1.dist-info/METADATA
mpipool-2.2.1.dist-info/RECORD
