Metadata-Version: 2.1
Name: mpipool
Version: 2.2.1
Summary: Implementation of the futures and multiprocessing Pool interfaces based on MPI.
Author-email: Robin De Schepper <robingilbert.deschepper@unipv.it>
Requires-Python: >=3.8
Requires-Dist: mpi4py>=3.0.3
Requires-Dist: dill>=0.3.3
Requires-Dist: errr>=1.0.0
Requires-Dist: tblib>=1.7.0
Requires-Dist: coverage~=7.0 ; extra == "test"
Provides-Extra: test
